iportal/__init__.py
iportal/cli.py
iportal/iportal.py
iportal-0.1.0.dist-info/AUTHORS.rst
iportal-0.1.0.dist-info/LICENSE
iportal-0.1.0.dist-info/METADATA
iportal-0.1.0.dist-info/WHEEL
iportal-0.1.0.dist-info/entry_points.txt
iportal-0.1.0.dist-info/top_level.txt
iportal-0.1.0.dist-info/RECORD
