Metadata-Version: 2.1
Name: iportal
Version: 0.1.0
Summary: data and workflow management
Home-page: https://github.com/malmstroem/iportal
Author: Lars Malmstroem
Author-email: lars@malmstroem.net
License: BSD license
Keywords: iportal
Platform: UNKNOWN
Classifier: Development Status :: 2 - Pre-Alpha
Classifier: Intended Audience :: Developers
Classifier: License :: OSI Approved :: BSD License
Classifier: Natural Language :: English
Classifier: Programming Language :: Python :: 2
Classifier: Programming Language :: Python :: 2.7
Classifier: Programming Language :: Python :: 3
Classifier: Programming Language :: Python :: 3.4
Classifier: Programming Language :: Python :: 3.5
Classifier: Programming Language :: Python :: 3.6
Classifier: Programming Language :: Python :: 3.7
Requires-Dist: Click (>=6.0)
Requires-Dist: keyring (>=17.0)
Requires-Dist: pybis (>=1.7)
